ranking.py
__pycache__/ranking.cpython-38.pyc
ranking.egg-info/PKG-INFO
ranking.egg-info/SOURCES.txt
ranking.egg-info/dependency_links.txt
ranking.egg-info/top_level.txt
ranking-0.3.2.dist-info/LICENSE
ranking-0.3.2.dist-info/METADATA
ranking-0.3.2.dist-info/WHEEL
ranking-0.3.2.dist-info/top_level.txt
ranking-0.3.2.dist-info/RECORD
